shellplot/__init__.py
shellplot/drawing.py
shellplot/pandas_api.py
shellplot/plots.py
shellplot/utils.py
shellplot/datasets/penguins.csv
shellplot-0.1.1.dist-info/AUTHORS.rst
shellplot-0.1.1.dist-info/LICENSE.txt
shellplot-0.1.1.dist-info/METADATA
shellplot-0.1.1.dist-info/WHEEL
shellplot-0.1.1.dist-info/entry_points.txt
shellplot-0.1.1.dist-info/top_level.txt
shellplot-0.1.1.dist-info/RECORD
