Metadata-Version: 2.1
Name: shellplot
Version: 0.1.1
Summary: Plotting from the command line
Home-page: https://github.com/CDonnerer/shellplot
Author: Christian Donnerer
Author-email: christian.donnerer@gmail.com
License: mit
Platform: any
Classifier: Development Status :: 4 - Beta
Classifier: Programming Language :: Python
Requires-Python: >=3.6
Requires-Dist: numpy
Requires-Dist: pandas
Provides-Extra: testing
Requires-Dist: pytest ; extra == 'testing'
Requires-Dist: pytest-cov ; extra == 'testing'
